{
  "name": "hbase_cluster Chef cookbook",
  "chef_cookbook_name": "hbase_cluster",
  "revision": "3.0.4",
  "uris": [
    "https://supermarket.chef.io/cookbooks/hbase_cluster",
    "https://supermarket.chef.io/cookbooks/hbase_cluster/download",
    "https://supermarket.chef.io/cookbooks/hbase_cluster/versions/3.0.4",
    "https://supermarket.chef.io/cookbooks/hbase_cluster/versions/3.0.4/download",
    "https://supermarket.chef.io/api/v1/cookbooks/hbase_cluster/versions/3.0.4",
    "https://supermarket.chef.io/api/v1/cookbooks/hbase_cluster",
    "https://supermarket.chef.io/api/v1/cookbooks/hbase_cluster/versions/3.0.4/download"
  ],
  "labels": [
    "Chef cookbook",
    "Databases",
    "Executable/Script/Chef Cookbook",
    "Type/Middleware/Runtime/Java",
    "Binding/Provider/HP",
    "Binding/Region/North America/US",
    "Mode/Executable/Script/Chef Cookbook",
    "Type/Devopsware/Orchestration/Cluster-based",
    "Type/Middleware/Data Store/Document-oriented/HBase",
    "Type/Middleware/Data Processing/Hadoop"
  ],
  "info_url": "https://supermarket.chef.io/cookbooks/hbase_cluster",
  "package_url": "https://supermarket.chef.io/api/v1/cookbooks/hbase_cluster/versions/3.0.4/download",
  "deprecated": false,
  "created": "2011-11-15T13:10:53.000Z",
  "updated": "2012-01-31T06:47:48.000Z",
  "description": "HBase: a massively-scalable high-throughput datastore based on the Hadoop HDFS",
  "maintainer": {
    "name": "mrflip",
    "email": "coders@infochimps.com"
  },
  "license": "Apache 2.0",
  "chef_foodcritic_failure": null,
  "chef_up_for_adoption": null,
  "rating": null,
  "followers_count": 9,
  "downloads_count": 3775264,
  "downloads_count_revision": 1258606,
  "latest": true,
  "gatherbase_origin": "chef-supermarket",
  "readme_name": "README.md",
  "readme": "# hbase chef cookbook\n\nHBase: a massively-scalable high-throughput datastore based on the Hadoop HDFS\n\n## Overview\n\nInstalls/Configures HBase\n\n## Recipes \n\n* `backup_tables`            - Cron job to backup tables to S3\n* `config`                   - Finalizes the config, writes out the config files\n* `dashboard`                - Simple dashboard for HBase config and state\n* `default`                  - Base configuration for hbase\n* `master`                   - HBase Master\n* `regionserver`             - HBase Regionserver\n* `stargate`                 - HBase Stargate: HTTP frontend to HBase\n* `thrift`                   - HBase Thrift Listener\n\n## Integration\n\nSupports platforms: debian and ubuntu\n\nCookbook dependencies:\n* java\n* apt\n* runit\n* volumes\n* metachef\n* dashpot\n* hadoop_cluster\n* zookeeper\n* ganglia\n\n\n## Attributes\n\n* `[:groups][:hbase][:gid]`           -  (default: \"304\")\n* `[:hbase][:tmp_dir]`                -  (default: \"/mnt/hbase/tmp\")\n* `[:hbase][:home_dir]`               -  (default: \"/usr/lib/hbase\")\n* `[:hbase][:conf_dir]`               -  (default: \"/etc/hbase/conf\")\n* `[:hbase][:log_dir]`                -  (default: \"/var/log/hbase\")\n* `[:hbase][:pid_dir]`                -  (default: \"/var/run/hbase\")\n* `[:hbase][:weekly_backup_tables]`   - \n* `[:hbase][:backup_location]`        -  (default: \"/mnt/hbase/bkup\")\n* `[:hbase][:master][:java_heap_size_max]` -  (default: \"1000m\")\n  - total size of the JVM heap (master)\n* `[:hbase][:master][:java_heap_size_new]` -  (default: \"256m\")\n  - size of the JVM \"New Generation/Eden\" heap segment (master)\n* `[:hbase][:master][:gc_tuning_opts]` -  (default: \"-XX:+UseConcMarkSweepGC -XX:+CMSIncrementalMode -XX:+AggressiveOpts\")\n  - JVM garbage collection tuning for the hbase master\n* `[:hbase][:master][:gc_log_opts]`   -  (default: \"-verbose:gc -XX:+PrintGCDetails -XX:+PrintGCTimeStamps\")\n  - What details to log about JVM garbage collection statistics for the hbase master\n* `[:hbase][:master][:run_state]`     -  (default: \"start\")\n* `[:hbase][:master][:port]`          -  (default: \"60000\")\n* `[:hbase][:master][:dash_port]`     -  (default: \"60010\")\n* `[:hbase][:master][:jmx_dash_port]` -  (default: \"10101\")\n* `[:hbase][:regionserver][:java_heap_size_max]` -  (default: \"2000m\")\n  - total size of the JVM heap (regionserver)\n* `[:hbase][:regionserver][:java_heap_size_new]` -  (default: \"256m\")\n  - size of the JVM \"New Generation/Eden\" heap segment (regionserver)\n* `[:hbase][:regionserver][:gc_tuning_opts]` -  (default: \"-XX:+UseConcMarkSweepGC -XX:+CMSIncrementalMode -XX:+AggressiveOpts -XX:CMSInitiatingOccupancyFraction=88\")\n  - JVM garbage collection tuning for the hbase regionserver\n* `[:hbase][:regionserver][:gc_log_opts]` -  (default: \"-verbose:gc -XX:+PrintGCDetails -XX:+PrintGCTimeStamps\")\n  - What details to log about JVM garbage collection statistics for the hbase regionserver\n* `[:hbase][:regionserver][:run_state]` -  (default: \"start\")\n* `[:hbase][:regionserver][:port]`    -  (default: \"60020\")\n* `[:hbase][:regionserver][:dash_port]` -  (default: \"60030\")\n* `[:hbase][:regionserver][:jmx_dash_port]` -  (default: \"10102\")\n* `[:hbase][:regionserver][:lease_period]` -  (default: \"60000\")\n  - hbase.regionserver.lease.period (default 60000) -- HRegion server lease period in\n    milliseconds. Default is 60 seconds. Clients must report in within this period else\n    they are considered dead.\n* `[:hbase][:regionserver][:handler_count]` -  (default: \"10\")\n  - hbase.regionserver.handler.count (default 10) -- Count of RPC Server instances spun up\n    on RegionServers. Same property is used by the Master for count of master handlers.\n* `[:hbase][:regionserver][:split_limit]` -  (default: \"2147483647\")\n  - hbase.regionserver.regionSplitLimit (default 2147483647) -- Limit for the number of\n    regions after which no more region splitting should take place. This is not a hard\n    limit for the number of regions but acts as a guideline for the regionserver to stop\n    splitting after a certain limit. Default is set to MAX_INT; i.e. do not block\n    splitting.\n* `[:hbase][:regionserver][:msg_period]` -  (default: \"3000\")\n  - hbase.regionserver.msginterval (default 3000) -- Interval between messages from the\n    RegionServer to Master in milliseconds.\n* `[:hbase][:regionserver][:log_flush_period]` -  (default: \"1000\")\n  - hbase.regionserver.optionallogflushinterval (default 1000) -- Sync the HLog to the HDFS\n    after this interval if it has not accumulated enough entries to trigger a\n    sync. Default 1 second. Units: milliseconds.\n* `[:hbase][:regionserver][:logroll_period]` -  (default: \"3600000\")\n  - hbase.regionserver.logroll.period (default 3600000) -- Period at which we will roll the\n    commit log regardless of how many edits it has.\n* `[:hbase][:regionserver][:split_check_period]` -  (default: \"20000\")\n  - hbase.regionserver.thread.splitcompactcheckfrequency (default 20000) -- How often a\n    region server runs the split/compaction check.\n* `[:hbase][:regionserver][:worker_period]` -  (default: \"10000\")\n  - hbase.server.thread.wakefrequency (default 10_000) -- Time to sleep in between searches\n    for work (in milliseconds).  Used as sleep interval by service threads such as log roller.\n* `[:hbase][:regionserver][:balancer_period]` -  (default: \"300000\")\n  - hbase.balancer.period (default 300000) -- Period at which the region balancer runs in\n    the Master.\n* `[:hbase][:regionserver][:balancer_slop]` -  (default: \"0\")\n  - hbase.regions.slop (default 0) -- Rebalance if any regionserver has more than\n    average + (average * slop) regions\n* `[:hbase][:regionserver][:max_filesize]` -  (default: \"268435456\")\n  - hbase.hregion.max.filesize (default 268435456) -- Maximum HStoreFile size. If any one of\n    a column families' HStoreFiles has grown to exceed this value, the hosting HRegion is\n    split in two.\n* `[:hbase][:regionserver][:hfile_block_size]` -  (default: \"65536\")\n  - hbase.mapreduce.hfileoutputformat.blocksize (default 65536) -- The mapreduce\n    HFileOutputFormat writes storefiles/hfiles.  This is the minimum hfile blocksize to\n    emit.  Usually in hbase, writing hfiles, the blocksize is gotten from the table schema\n    (HColumnDescriptor) but in the mapreduce outputformat context, we don't have access to\n    the schema so get blocksize from Configuation.  The smaller you make the blocksize,\n    the bigger your index and the less you fetch on a random-access.  Set the blocksize\n    down if you have small cells and want faster random-access of individual cells.\n* `[:hbase][:regionserver][:required_codecs]` - \n  - hbase.regionserver.codecs (default \"\") -- To have a RegionServer test a set of\n    codecs and fail-to-start if any code is missing or misinstalled, add the\n    configuration hbase.regionserver.codecs to your hbase-site.xml with a value of\n    codecs to test on startup. For example if the hbase.regionserver.codecs value\n    is \"lzo,gz\" and if lzo is not present or improperly installed, the misconfigured\n    RegionServer will fail to start.\n* `[:hbase][:regionserver][:block_cache_size]` -  (default: \"0.2\")\n  - hfile.block.cache.size (default 0.2) -- Percentage of maximum heap (-Xmx setting) to\n    allocate to block cache used by HFile/StoreFile. Default of 0.2 means allocate 20%.\n    Set to 0 to disable.\n* `[:hbase][:regionserver][:hash_type]` -  (default: \"murmur\")\n  - hbase.hash.type (default murmur) -- The hashing algorithm for use in HashFunction. Two\n    values are supported now: murmur (MurmurHash) and jenkins (JenkinsHash).  Used by\n    bloom filters.\n* `[:hbase][:stargate][:run_state]`   -  (default: \"start\")\n* `[:hbase][:stargate][:port]`        -  (default: \"8080\")\n* `[:hbase][:stargate][:jmx_dash_port]` -  (default: \"10105\")\n* `[:hbase][:stargate][:readonly]`    - \n  - hbase.rest.readonly (default false) -- Defines the mode the REST server will be started\n    in. Possible values are: false: All HTTP methods are permitted - GET/PUT/POST/DELETE.\n    true: Only the GET method is permitted.\n* `[:hbase][:thrift][:run_state]`     -  (default: \"start\")\n* `[:hbase][:thrift][:jmx_dash_port]` -  (default: \"10104\")\n* `[:hbase][:zookeeper][:jmx_dash_port]` -  (default: \"10103\")\n* `[:hbase][:zookeeper][:peer_port]`  -  (default: \"2888\")\n* `[:hbase][:zookeeper][:leader_port]` -  (default: \"3888\")\n* `[:hbase][:zookeeper][:client_port]` -  (default: \"2181\")\n* `[:hbase][:zookeeper][:session_timeout]` -  (default: \"180000\")\n  - zookeeper.session.timeout (default 180_000) -- ZooKeeper session timeout.  HBase passes\n    this to the zk quorum as suggested maximum time for a session.  See\n    http://hadoop.apache.org/zookeeper/docs/current/zookeeperProgrammers.html#ch_zkSessions\n    \"The client sends a requested timeout, the server responds with the timeout that it\n    can give the client. \" In milliseconds.\n* `[:hbase][:zookeeper][:znode_parent]` -  (default: \"/hbase\")\n  - zookeeper.znode.parent (default \"/hbase\") -- Root ZNode for HBase in\n    ZooKeeper. All of HBase's ZooKeeper files that are configured with a\n    relative path will go under this node.  By default, all of HBase's ZooKeeper\n    file path are configured with a relative path, so they will all go under\n    this directory unless changed.\n* `[:hbase][:zookeeper][:znode_rootserver]` -  (default: \"root-region-server\")\n  - zookeeper.znode.rootserver (default root-region-server) -- Path to ZNode\n    holding root region location. This is written by the master and read by\n    clients and region servers. If a relative path is given, the parent folder\n    will be ${zookeeper.znode.parent}. By default, this means the root location\n    is stored at /hbase/root-region-server.\n* `[:hbase][:zookeeper][:max_client_connections]` -  (default: \"2000\")\n  - hbase.zookeeper.property.maxClientCnxns (default 2000) -- Limit on number of concurrent\n    connections (at the socket level) that a single client, identified by IP address, may\n    make to a single member of the ZooKeeper ensemble. Set high to avoid zk connection\n    issues running standalone and pseudo-distributed.\n* `[:hbase][:client][:write_buffer]`  -  (default: \"2097152\")\n  - hbase.client.write.buffer (default 2097152) Default size of the HTable client write\n    buffer in bytes.  A bigger buffer takes more memory -- on both the client and server\n    side since server instantiates the passed write buffer to process it -- but a larger\n    buffer size reduces the number of RPCs made.  For an estimate of server-side\n    memory-used, evaluate\n    hbase.client.write.buffer * hbase.regionserver.handler.count\n* `[:hbase][:client][:pause_period_ms]` -  (default: \"1000\")\n  - hbase.client.pause (default 1000) -- General client pause value.  Used mostly as value\n    to wait before running a retry of a failed get, region lookup, etc.\n* `[:hbase][:client][:retry_count]`   -  (default: \"10\")\n  - hbase.client.retries.number (default 10) -- Maximum retries.  Used as maximum for all\n    retryable operations such as fetching of the root region from root region server,\n    getting a cell's value, starting a row update, etc.\n* `[:hbase][:client][:scanner_prefetch_rows]` -  (default: \"1\")\n  - hbase.client.scanner.caching (default 1) -- Number of rows that will be fetched when\n    calling next on a scanner if it is not served from (local, client) memory. Higher\n    caching values will enable faster scanners but will eat up more memory and some calls\n    of next may take longer and longer times when the cache is empty.  Do not set this\n    value such that the time between invocations is greater than the scanner timeout;\n    i.e. hbase.regionserver.lease.period\n* `[:hbase][:client][:max_keyvalue_size]` -  (default: \"10485760\")\n  - hbase.client.keyvalue.maxsize (default 10485760) -- Specifies the combined maximum\n    allowed size of a KeyValue instance. This is to set an upper boundary for a single\n    entry saved in a storage file. Since they cannot be split it helps avoiding that a\n    region cannot be split any further because the data is too large. It seems wise to set\n    this to a fraction of the maximum region size. Setting it to zero or less disables the\n    check.\n* `[:hbase][:memstore][:flush_upper_heap_pct]` -  (default: \"0.4\")\n  - hbase.regionserver.global.memstore.upperLimit (default 0.4) -- Maximum size of all\n    memstores in a region server before new updates are blocked and flushes are\n    forced. Defaults to 40% of heap\n* `[:hbase][:memstore][:flush_lower_heap_pct]` -  (default: \"0.35\")\n  - hbase.regionserver.global.memstore.lowerLimit (default 0.35) -- When memstores are being\n    forced to flush to make room in memory, keep flushing until we hit this mark. Defaults\n    to 35% of heap.  This value equal to hbase.regionserver.global.memstore.upperLimit\n    causes the minimum possible flushing to occur when updates are blocked due to memstore\n    limiting.\n* `[:hbase][:memstore][:flush_size_trigger]` -  (default: \"67108864\")\n  - hbase.hregion.memstore.flush.size (default 67108864) -- Memstore will be flushed to disk\n    if size of the memstore exceeds this number of bytes.  Value is checked by a thread\n    that runs every hbase.server.thread.wakefrequency.\n* `[:hbase][:memstore][:preflush_trigger]` -  (default: \"5242880\")\n  - hbase.hregion.preclose.flush.size (default 5 mb) -- If the memstores in a region are\n    this size or larger when we go to close, run a \"pre-flush\" to clear out memstores\n    before we put up the region closed flag and take the region offline.  On close, a\n    flush is run under the close flag to empty memory.  During this time the region is\n    offline and we are not taking on any writes.  If the memstore content is large, this\n    flush could take a long time to complete.  The preflush is meant to clean out the bulk\n    of the memstore before putting up the close flag and taking the region offline so the\n    flush that runs under the close flag has little to do.\n* `[:hbase][:memstore][:flush_stall_trigger]` -  (default: \"8\")\n  - hbase.hregion.memstore.block.multiplier (default 2) -- Block updates if memstore has\n    hbase.hregion.block.memstore time hbase.hregion.flush.size bytes.  Useful preventing\n    runaway memstore during spikes in update traffic.  Without an upper-bound, memstore\n    fills such that when it flushes the resultant flush files take a long time to compact\n    or split, or worse, we OOME.\n* `[:hbase][:memstore][:mslab_enabled]` - \n  - hbase.hregion.memstore.mslab.enabled (default false) -- Experimental: Enables the\n    MemStore-Local Allocation Buffer, a feature which works to prevent heap fragmentation\n    under heavy write loads. This can reduce the frequency of stop-the-world GC pauses on\n    large heaps.\n* `[:hbase][:compaction][:files_trigger]` -  (default: \"3\")\n  - hbase.hstore.compactionThreshold (default 3) -- If more than this number of HStoreFiles\n    in any one HStore (one HStoreFile is written per flush of memstore) then a compaction\n    is run to rewrite all HStoreFiles files as one.  Larger numbers put off compaction but\n    when it runs, it takes longer to complete.\n* `[:hbase][:compaction][:pause_trigger]` -  (default: \"7\")\n  - hbase.hstore.blockingStoreFiles (default 7) -- If more than this number of StoreFiles in\n    any one Store (one StoreFile is written per flush of MemStore) then updates are\n    blocked for this HRegion until a compaction is completed, or until\n    hbase.hstore.blockingWaitTime has been exceeded.\n* `[:hbase][:compaction][:pause_time]` -  (default: \"90000\")\n  - hbase.hstore.blockingWaitTime (default 90_000) -- The time an HRegion will block updates\n    for after hitting the StoreFile limit defined by hbase.hstore.blockingStoreFiles.\n    After this time has elapsed, the HRegion will stop blocking updates even if a\n    compaction has not been completed.  Default: 90 seconds.\n* `[:hbase][:compaction][:max_combine_files]` -  (default: \"10\")\n  - hbase.hstore.compaction.max (default 10) -- Max number of HStoreFiles to compact per\n    'minor' compaction.\n* `[:hbase][:compaction][:period]`    -  (default: \"86400000\")\n  - hbase.hregion.majorcompaction (default 86400000) -- The time (in miliseconds) between\n    'major' compactions of all HStoreFiles in a region.  Default: 1 day.  Set to 0 to\n    disable automated major compactions.\n* `[:users][:hbase][:uid]`            -  (default: \"304\")\n* `[:tuning][:ulimit][:hbase]`        - \n\n## License and Author\n\nAuthor::                Chris Howe - Infochimps, Inc (<coders@infochimps.com>)\nCopyright::             2011, Chris Howe - Infochimps, Inc\n\nLicensed under the Apache License, Version 2.0 (the \"License\");\nyou may not use this file except in compliance with the License.\nYou may obtain a copy of the License at\n\n    http://www.apache.org/licenses/LICENSE-2.0\n\nUnless required by applicable law or agreed to in writing, software\ndistributed under the License is distributed on an \"AS IS\" BASIS,\nWITHOUT WARRANTIES OR CONDITIONS OF ANY KIND, either express or implied.\nSee the License for the specific language governing permissions and\nlimitations under the License.\n\n> readme generated by [cluster_chef](http://github.com/infochimps/cluster_chef)'s cookbook_munger\n",
  "requires": [
    {
      "kind": "host",
      "label": "debian",
      "revision": ">= 0.0.0",
      "one_of_group": "os"
    },
    {
      "kind": "host",
      "label": "ubuntu",
      "revision": ">= 0.0.0",
      "one_of_group": "os"
    },
    {
      "kind": "env",
      "uri": "https://supermarket.chef.io/cookbooks/java",
      "revision": ">= 0.0.0",
      "self_resolve": true
    },
    {
      "kind": "env",
      "uri": "https://supermarket.chef.io/cookbooks/apt",
      "revision": ">= 0.0.0",
      "self_resolve": true
    },
    {
      "kind": "env",
      "uri": "https://supermarket.chef.io/cookbooks/runit",
      "revision": ">= 0.0.0",
      "self_resolve": true
    },
    {
      "kind": "env",
      "uri": "https://supermarket.chef.io/cookbooks/volumes",
      "revision": ">= 0.0.0",
      "self_resolve": true
    },
    {
      "kind": "env",
      "uri": "https://supermarket.chef.io/cookbooks/metachef",
      "revision": ">= 0.0.0",
      "self_resolve": true
    },
    {
      "kind": "env",
      "uri": "https://supermarket.chef.io/cookbooks/dashpot",
      "revision": ">= 0.0.0",
      "self_resolve": true
    },
    {
      "kind": "env",
      "uri": "https://supermarket.chef.io/cookbooks/hadoop_cluster",
      "revision": ">= 0.0.0",
      "self_resolve": true
    },
    {
      "kind": "env",
      "uri": "https://supermarket.chef.io/cookbooks/zookeeper",
      "revision": ">= 0.0.0",
      "self_resolve": true
    },
    {
      "kind": "env",
      "uri": "https://supermarket.chef.io/cookbooks/ganglia",
      "revision": ">= 0.0.0",
      "self_resolve": true
    }
  ],
  "chef_recipes": {
    "hbase::backup_tables": "Cron job to backup tables to S3",
    "hbase::default": "Base configuration for hbase",
    "hbase::master": "HBase Master",
    "hbase::regionserver": "HBase Regionserver",
    "hbase::stargate": "HBase Stargate: HTTP frontend to HBase",
    "hbase::thrift": "HBase Thrift Listener",
    "hbase::dashboard": "Simple dashboard for HBase config and state",
    "hbase::config": "Finalizes the config, writes out the config files"
  },
  "parameters": {
    "groups/hbase/gid": {
      "display_name": "",
      "description": "",
      "default": "304",
      "choice": [],
      "calculated": false,
      "type": "string",
      "required": "optional",
      "recipes": [],
      "mapping": "cookbook_attribute"
    },
    "hbase/tmp_dir": {
      "display_name": "",
      "description": "",
      "default": "/mnt/hbase/tmp",
      "choice": [],
      "calculated": false,
      "type": "string",
      "required": "optional",
      "recipes": [],
      "mapping": "cookbook_attribute"
    },
    "hbase/home_dir": {
      "display_name": "",
      "description": "",
      "default": "/usr/lib/hbase",
      "choice": [],
      "calculated": false,
      "type": "string",
      "required": "optional",
      "recipes": [],
      "mapping": "cookbook_attribute"
    },
    "hbase/conf_dir": {
      "display_name": "",
      "description": "",
      "default": "/etc/hbase/conf",
      "choice": [],
      "calculated": false,
      "type": "string",
      "required": "optional",
      "recipes": [],
      "mapping": "cookbook_attribute"
    },
    "hbase/log_dir": {
      "display_name": "",
      "description": "",
      "default": "/var/log/hbase",
      "choice": [],
      "calculated": false,
      "type": "string",
      "required": "optional",
      "recipes": [],
      "mapping": "cookbook_attribute"
    },
    "hbase/pid_dir": {
      "display_name": "",
      "description": "",
      "default": "/var/run/hbase",
      "choice": [],
      "calculated": false,
      "type": "string",
      "required": "optional",
      "recipes": [],
      "mapping": "cookbook_attribute"
    },
    "hbase/weekly_backup_tables": {
      "display_name": "",
      "description": "",
      "default": "",
      "choice": [],
      "calculated": false,
      "type": "string",
      "required": "optional",
      "recipes": [],
      "mapping": "cookbook_attribute"
    },
    "hbase/backup_location": {
      "display_name": "",
      "description": "",
      "default": "/mnt/hbase/bkup",
      "choice": [],
      "calculated": false,
      "type": "string",
      "required": "optional",
      "recipes": [],
      "mapping": "cookbook_attribute"
    },
    "hbase/master/java_heap_size_max": {
      "display_name": "",
      "description": "total size of the JVM heap (master)",
      "default": "1000m",
      "choice": [],
      "calculated": false,
      "type": "string",
      "required": "optional",
      "recipes": [],
      "mapping": "cookbook_attribute"
    },
    "hbase/master/java_heap_size_new": {
      "display_name": "",
      "description": "size of the JVM \"New Generation/Eden\" heap segment (master)",
      "default": "256m",
      "choice": [],
      "calculated": false,
      "type": "string",
      "required": "optional",
      "recipes": [],
      "mapping": "cookbook_attribute"
    },
    "hbase/master/gc_tuning_opts": {
      "display_name": "",
      "description": "JVM garbage collection tuning for the hbase master",
      "default": "-XX:+UseConcMarkSweepGC -XX:+CMSIncrementalMode -XX:+AggressiveOpts",
      "choice": [],
      "calculated": false,
      "type": "string",
      "required": "optional",
      "recipes": [],
      "mapping": "cookbook_attribute"
    },
    "hbase/master/gc_log_opts": {
      "display_name": "",
      "description": "What details to log about JVM garbage collection statistics for the hbase master",
      "default": "-verbose:gc -XX:+PrintGCDetails -XX:+PrintGCTimeStamps",
      "choice": [],
      "calculated": false,
      "type": "string",
      "required": "optional",
      "recipes": [],
      "mapping": "cookbook_attribute"
    },
    "hbase/master/run_state": {
      "display_name": "",
      "description": "",
      "type": "array",
      "default": "start",
      "choice": [],
      "calculated": false,
      "required": "optional",
      "recipes": [],
      "mapping": "cookbook_attribute"
    },
    "hbase/master/port": {
      "display_name": "",
      "description": "",
      "default": "60000",
      "choice": [],
      "calculated": false,
      "type": "string",
      "required": "optional",
      "recipes": [],
      "mapping": "cookbook_attribute"
    },
    "hbase/master/dash_port": {
      "display_name": "",
      "description": "",
      "default": "60010",
      "choice": [],
      "calculated": false,
      "type": "string",
      "required": "optional",
      "recipes": [],
      "mapping": "cookbook_attribute"
    },
    "hbase/master/jmx_dash_port": {
      "display_name": "",
      "description": "",
      "default": "10101",
      "choice": [],
      "calculated": false,
      "type": "string",
      "required": "optional",
      "recipes": [],
      "mapping": "cookbook_attribute"
    },
    "hbase/regionserver/java_heap_size_max": {
      "display_name": "",
      "description": "total size of the JVM heap (regionserver)",
      "default": "2000m",
      "choice": [],
      "calculated": false,
      "type": "string",
      "required": "optional",
      "recipes": [],
      "mapping": "cookbook_attribute"
    },
    "hbase/regionserver/java_heap_size_new": {
      "display_name": "",
      "description": "size of the JVM \"New Generation/Eden\" heap segment (regionserver)",
      "default": "256m",
      "choice": [],
      "calculated": false,
      "type": "string",
      "required": "optional",
      "recipes": [],
      "mapping": "cookbook_attribute"
    },
    "hbase/regionserver/gc_tuning_opts": {
      "display_name": "",
      "description": "JVM garbage collection tuning for the hbase regionserver",
      "default": "-XX:+UseConcMarkSweepGC -XX:+CMSIncrementalMode -XX:+AggressiveOpts -XX:CMSInitiatingOccupancyFraction=88",
      "choice": [],
      "calculated": false,
      "type": "string",
      "required": "optional",
      "recipes": [],
      "mapping": "cookbook_attribute"
    },
    "hbase/regionserver/gc_log_opts": {
      "display_name": "",
      "description": "What details to log about JVM garbage collection statistics for the hbase regionserver",
      "default": "-verbose:gc -XX:+PrintGCDetails -XX:+PrintGCTimeStamps",
      "choice": [],
      "calculated": false,
      "type": "string",
      "required": "optional",
      "recipes": [],
      "mapping": "cookbook_attribute"
    },
    "hbase/regionserver/run_state": {
      "display_name": "",
      "description": "",
      "type": "array",
      "default": "start",
      "choice": [],
      "calculated": false,
      "required": "optional",
      "recipes": [],
      "mapping": "cookbook_attribute"
    },
    "hbase/regionserver/port": {
      "display_name": "",
      "description": "",
      "default": "60020",
      "choice": [],
      "calculated": false,
      "type": "string",
      "required": "optional",
      "recipes": [],
      "mapping": "cookbook_attribute"
    },
    "hbase/regionserver/dash_port": {
      "display_name": "",
      "description": "",
      "default": "60030",
      "choice": [],
      "calculated": false,
      "type": "string",
      "required": "optional",
      "recipes": [],
      "mapping": "cookbook_attribute"
    },
    "hbase/regionserver/jmx_dash_port": {
      "display_name": "",
      "description": "",
      "default": "10102",
      "choice": [],
      "calculated": false,
      "type": "string",
      "required": "optional",
      "recipes": [],
      "mapping": "cookbook_attribute"
    },
    "hbase/regionserver/lease_period": {
      "display_name": "",
      "description": "hbase.regionserver.lease.period (default 60000) -- HRegion server lease period in\nmilliseconds. Default is 60 seconds. Clients must report in within this period else\nthey are considered dead.",
      "default": "60000",
      "choice": [],
      "calculated": false,
      "type": "string",
      "required": "optional",
      "recipes": [],
      "mapping": "cookbook_attribute"
    },
    "hbase/regionserver/handler_count": {
      "display_name": "",
      "description": "hbase.regionserver.handler.count (default 10) -- Count of RPC Server instances spun up\non RegionServers. Same property is used by the Master for count of master handlers.",
      "default": "10",
      "choice": [],
      "calculated": false,
      "type": "string",
      "required": "optional",
      "recipes": [],
      "mapping": "cookbook_attribute"
    },
    "hbase/regionserver/split_limit": {
      "display_name": "",
      "description": "hbase.regionserver.regionSplitLimit (default 2147483647) -- Limit for the number of\nregions after which no more region splitting should take place. This is not a hard\nlimit for the number of regions but acts as a guideline for the regionserver to stop\nsplitting after a certain limit. Default is set to MAX_INT; i.e. do not block\nsplitting.",
      "default": "2147483647",
      "choice": [],
      "calculated": false,
      "type": "string",
      "required": "optional",
      "recipes": [],
      "mapping": "cookbook_attribute"
    },
    "hbase/regionserver/msg_period": {
      "display_name": "",
      "description": "hbase.regionserver.msginterval (default 3000) -- Interval between messages from the\nRegionServer to Master in milliseconds.",
      "default": "3000",
      "choice": [],
      "calculated": false,
      "type": "string",
      "required": "optional",
      "recipes": [],
      "mapping": "cookbook_attribute"
    },
    "hbase/regionserver/log_flush_period": {
      "display_name": "",
      "description": "hbase.regionserver.optionallogflushinterval (default 1000) -- Sync the HLog to the HDFS\nafter this interval if it has not accumulated enough entries to trigger a\nsync. Default 1 second. Units: milliseconds.",
      "default": "1000",
      "choice": [],
      "calculated": false,
      "type": "string",
      "required": "optional",
      "recipes": [],
      "mapping": "cookbook_attribute"
    },
    "hbase/regionserver/logroll_period": {
      "display_name": "",
      "description": "hbase.regionserver.logroll.period (default 3600000) -- Period at which we will roll the\ncommit log regardless of how many edits it has.",
      "default": "3600000",
      "choice": [],
      "calculated": false,
      "type": "string",
      "required": "optional",
      "recipes": [],
      "mapping": "cookbook_attribute"
    },
    "hbase/regionserver/split_check_period": {
      "display_name": "",
      "description": "hbase.regionserver.thread.splitcompactcheckfrequency (default 20000) -- How often a\nregion server runs the split/compaction check.",
      "default": "20000",
      "choice": [],
      "calculated": false,
      "type": "string",
      "required": "optional",
      "recipes": [],
      "mapping": "cookbook_attribute"
    },
    "hbase/regionserver/worker_period": {
      "display_name": "",
      "description": "hbase.server.thread.wakefrequency (default 10_000) -- Time to sleep in between searches\nfor work (in milliseconds).  Used as sleep interval by service threads such as log roller.",
      "default": "10000",
      "choice": [],
      "calculated": false,
      "type": "string",
      "required": "optional",
      "recipes": [],
      "mapping": "cookbook_attribute"
    },
    "hbase/regionserver/balancer_period": {
      "display_name": "",
      "description": "hbase.balancer.period (default 300000) -- Period at which the region balancer runs in\nthe Master.",
      "default": "300000",
      "choice": [],
      "calculated": false,
      "type": "string",
      "required": "optional",
      "recipes": [],
      "mapping": "cookbook_attribute"
    },
    "hbase/regionserver/balancer_slop": {
      "display_name": "",
      "description": "hbase.regions.slop (default 0) -- Rebalance if any regionserver has more than\naverage + (average * slop) regions",
      "default": "0",
      "choice": [],
      "calculated": false,
      "type": "string",
      "required": "optional",
      "recipes": [],
      "mapping": "cookbook_attribute"
    },
    "hbase/regionserver/max_filesize": {
      "display_name": "",
      "description": "hbase.hregion.max.filesize (default 268435456) -- Maximum HStoreFile size. If any one of\na column families' HStoreFiles has grown to exceed this value, the hosting HRegion is\nsplit in two.",
      "default": "268435456",
      "choice": [],
      "calculated": false,
      "type": "string",
      "required": "optional",
      "recipes": [],
      "mapping": "cookbook_attribute"
    },
    "hbase/regionserver/hfile_block_size": {
      "display_name": "",
      "description": "hbase.mapreduce.hfileoutputformat.blocksize (default 65536) -- The mapreduce\nHFileOutputFormat writes storefiles/hfiles.  This is the minimum hfile blocksize to\nemit.  Usually in hbase, writing hfiles, the blocksize is gotten from the table schema\n(HColumnDescriptor) but in the mapreduce outputformat context, we don't have access to\nthe schema so get blocksize from Configuation.  The smaller you make the blocksize,\nthe bigger your index and the less you fetch on a random-access.  Set the blocksize\ndown if you have small cells and want faster random-access of individual cells.",
      "default": "65536",
      "choice": [],
      "calculated": false,
      "type": "string",
      "required": "optional",
      "recipes": [],
      "mapping": "cookbook_attribute"
    },
    "hbase/regionserver/required_codecs": {
      "display_name": "",
      "description": "hbase.regionserver.codecs (default \"\") -- To have a RegionServer test a set of\ncodecs and fail-to-start if any code is missing or misinstalled, add the\nconfiguration hbase.regionserver.codecs to your hbase-site.xml with a value of\ncodecs to test on startup. For example if the hbase.regionserver.codecs value\nis \"lzo,gz\" and if lzo is not present or improperly installed, the misconfigured\nRegionServer will fail to start.",
      "default": "",
      "choice": [],
      "calculated": false,
      "type": "string",
      "required": "optional",
      "recipes": [],
      "mapping": "cookbook_attribute"
    },
    "hbase/regionserver/block_cache_size": {
      "display_name": "",
      "description": "hfile.block.cache.size (default 0.2) -- Percentage of maximum heap (-Xmx setting) to\nallocate to block cache used by HFile/StoreFile. Default of 0.2 means allocate 20%.\nSet to 0 to disable.",
      "default": "0.2",
      "choice": [],
      "calculated": false,
      "type": "string",
      "required": "optional",
      "recipes": [],
      "mapping": "cookbook_attribute"
    },
    "hbase/regionserver/hash_type": {
      "display_name": "",
      "description": "hbase.hash.type (default murmur) -- The hashing algorithm for use in HashFunction. Two\nvalues are supported now: murmur (MurmurHash) and jenkins (JenkinsHash).  Used by\nbloom filters.",
      "default": "murmur",
      "choice": [],
      "calculated": false,
      "type": "string",
      "required": "optional",
      "recipes": [],
      "mapping": "cookbook_attribute"
    },
    "hbase/stargate/run_state": {
      "display_name": "",
      "description": "",
      "type": "array",
      "default": "start",
      "choice": [],
      "calculated": false,
      "required": "optional",
      "recipes": [],
      "mapping": "cookbook_attribute"
    },
    "hbase/stargate/port": {
      "display_name": "",
      "description": "",
      "default": "8080",
      "choice": [],
      "calculated": false,
      "type": "string",
      "required": "optional",
      "recipes": [],
      "mapping": "cookbook_attribute"
    },
    "hbase/stargate/jmx_dash_port": {
      "display_name": "",
      "description": "",
      "default": "10105",
      "choice": [],
      "calculated": false,
      "type": "string",
      "required": "optional",
      "recipes": [],
      "mapping": "cookbook_attribute"
    },
    "hbase/stargate/readonly": {
      "display_name": "",
      "description": "hbase.rest.readonly (default false) -- Defines the mode the REST server will be started\nin. Possible values are: false: All HTTP methods are permitted - GET/PUT/POST/DELETE.\ntrue: Only the GET method is permitted.",
      "default": "",
      "choice": [],
      "calculated": false,
      "type": "string",
      "required": "optional",
      "recipes": [],
      "mapping": "cookbook_attribute"
    },
    "hbase/thrift/run_state": {
      "display_name": "",
      "description": "",
      "default": "start",
      "choice": [],
      "calculated": false,
      "type": "string",
      "required": "optional",
      "recipes": [],
      "mapping": "cookbook_attribute"
    },
    "hbase/thrift/jmx_dash_port": {
      "display_name": "",
      "description": "",
      "default": "10104",
      "choice": [],
      "calculated": false,
      "type": "string",
      "required": "optional",
      "recipes": [],
      "mapping": "cookbook_attribute"
    },
    "hbase/zookeeper/jmx_dash_port": {
      "display_name": "",
      "description": "",
      "default": "10103",
      "choice": [],
      "calculated": false,
      "type": "string",
      "required": "optional",
      "recipes": [],
      "mapping": "cookbook_attribute"
    },
    "hbase/zookeeper/peer_port": {
      "display_name": "",
      "description": "",
      "default": "2888",
      "choice": [],
      "calculated": false,
      "type": "string",
      "required": "optional",
      "recipes": [],
      "mapping": "cookbook_attribute"
    },
    "hbase/zookeeper/leader_port": {
      "display_name": "",
      "description": "",
      "default": "3888",
      "choice": [],
      "calculated": false,
      "type": "string",
      "required": "optional",
      "recipes": [],
      "mapping": "cookbook_attribute"
    },
    "hbase/zookeeper/client_port": {
      "display_name": "",
      "description": "",
      "default": "2181",
      "choice": [],
      "calculated": false,
      "type": "string",
      "required": "optional",
      "recipes": [],
      "mapping": "cookbook_attribute"
    },
    "hbase/zookeeper/session_timeout": {
      "display_name": "",
      "description": "zookeeper.session.timeout (default 180_000) -- ZooKeeper session timeout.  HBase passes\nthis to the zk quorum as suggested maximum time for a session.  See\nhttp://hadoop.apache.org/zookeeper/docs/current/zookeeperProgrammers.html#ch_zkSessions\n\"The client sends a requested timeout, the server responds with the timeout that it\ncan give the client. \" In milliseconds.",
      "default": "180000",
      "choice": [],
      "calculated": false,
      "type": "string",
      "required": "optional",
      "recipes": [],
      "mapping": "cookbook_attribute"
    },
    "hbase/zookeeper/znode_parent": {
      "display_name": "",
      "description": "zookeeper.znode.parent (default \"/hbase\") -- Root ZNode for HBase in\nZooKeeper. All of HBase's ZooKeeper files that are configured with a\nrelative path will go under this node.  By default, all of HBase's ZooKeeper\nfile path are configured with a relative path, so they will all go under\nthis directory unless changed.",
      "default": "/hbase",
      "choice": [],
      "calculated": false,
      "type": "string",
      "required": "optional",
      "recipes": [],
      "mapping": "cookbook_attribute"
    },
    "hbase/zookeeper/znode_rootserver": {
      "display_name": "",
      "description": "zookeeper.znode.rootserver (default root-region-server) -- Path to ZNode\nholding root region location. This is written by the master and read by\nclients and region servers. If a relative path is given, the parent folder\nwill be ${zookeeper.znode.parent}. By default, this means the root location\nis stored at /hbase/root-region-server.",
      "default": "root-region-server",
      "choice": [],
      "calculated": false,
      "type": "string",
      "required": "optional",
      "recipes": [],
      "mapping": "cookbook_attribute"
    },
    "hbase/zookeeper/max_client_connections": {
      "display_name": "",
      "description": "hbase.zookeeper.property.maxClientCnxns (default 2000) -- Limit on number of concurrent\nconnections (at the socket level) that a single client, identified by IP address, may\nmake to a single member of the ZooKeeper ensemble. Set high to avoid zk connection\nissues running standalone and pseudo-distributed.",
      "default": "2000",
      "choice": [],
      "calculated": false,
      "type": "string",
      "required": "optional",
      "recipes": [],
      "mapping": "cookbook_attribute"
    },
    "hbase/client/write_buffer": {
      "display_name": "",
      "description": "hbase.client.write.buffer (default 2097152) Default size of the HTable client write\nbuffer in bytes.  A bigger buffer takes more memory -- on both the client and server\nside since server instantiates the passed write buffer to process it -- but a larger\nbuffer size reduces the number of RPCs made.  For an estimate of server-side\nmemory-used, evaluate\nhbase.client.write.buffer * hbase.regionserver.handler.count",
      "default": "2097152",
      "choice": [],
      "calculated": false,
      "type": "string",
      "required": "optional",
      "recipes": [],
      "mapping": "cookbook_attribute"
    },
    "hbase/client/pause_period_ms": {
      "display_name": "",
      "description": "hbase.client.pause (default 1000) -- General client pause value.  Used mostly as value\nto wait before running a retry of a failed get, region lookup, etc.",
      "default": "1000",
      "choice": [],
      "calculated": false,
      "type": "string",
      "required": "optional",
      "recipes": [],
      "mapping": "cookbook_attribute"
    },
    "hbase/client/retry_count": {
      "display_name": "",
      "description": "hbase.client.retries.number (default 10) -- Maximum retries.  Used as maximum for all\nretryable operations such as fetching of the root region from root region server,\ngetting a cell's value, starting a row update, etc.",
      "default": "10",
      "choice": [],
      "calculated": false,
      "type": "string",
      "required": "optional",
      "recipes": [],
      "mapping": "cookbook_attribute"
    },
    "hbase/client/scanner_prefetch_rows": {
      "display_name": "",
      "description": "hbase.client.scanner.caching (default 1) -- Number of rows that will be fetched when\ncalling next on a scanner if it is not served from (local, client) memory. Higher\ncaching values will enable faster scanners but will eat up more memory and some calls\nof next may take longer and longer times when the cache is empty.  Do not set this\nvalue such that the time between invocations is greater than the scanner timeout;\ni.e. hbase.regionserver.lease.period",
      "default": "1",
      "choice": [],
      "calculated": false,
      "type": "string",
      "required": "optional",
      "recipes": [],
      "mapping": "cookbook_attribute"
    },
    "hbase/client/max_keyvalue_size": {
      "display_name": "",
      "description": "hbase.client.keyvalue.maxsize (default 10485760) -- Specifies the combined maximum\nallowed size of a KeyValue instance. This is to set an upper boundary for a single\nentry saved in a storage file. Since they cannot be split it helps avoiding that a\nregion cannot be split any further because the data is too large. It seems wise to set\nthis to a fraction of the maximum region size. Setting it to zero or less disables the\ncheck.",
      "default": "10485760",
      "choice": [],
      "calculated": false,
      "type": "string",
      "required": "optional",
      "recipes": [],
      "mapping": "cookbook_attribute"
    },
    "hbase/memstore/flush_upper_heap_pct": {
      "display_name": "",
      "description": "hbase.regionserver.global.memstore.upperLimit (default 0.4) -- Maximum size of all\nmemstores in a region server before new updates are blocked and flushes are\nforced. Defaults to 40% of heap",
      "default": "0.4",
      "choice": [],
      "calculated": false,
      "type": "string",
      "required": "optional",
      "recipes": [],
      "mapping": "cookbook_attribute"
    },
    "hbase/memstore/flush_lower_heap_pct": {
      "display_name": "",
      "description": "hbase.regionserver.global.memstore.lowerLimit (default 0.35) -- When memstores are being\nforced to flush to make room in memory, keep flushing until we hit this mark. Defaults\nto 35% of heap.  This value equal to hbase.regionserver.global.memstore.upperLimit\ncauses the minimum possible flushing to occur when updates are blocked due to memstore\nlimiting.",
      "default": "0.35",
      "choice": [],
      "calculated": false,
      "type": "string",
      "required": "optional",
      "recipes": [],
      "mapping": "cookbook_attribute"
    },
    "hbase/memstore/flush_size_trigger": {
      "display_name": "",
      "description": "hbase.hregion.memstore.flush.size (default 67108864) -- Memstore will be flushed to disk\nif size of the memstore exceeds this number of bytes.  Value is checked by a thread\nthat runs every hbase.server.thread.wakefrequency.",
      "default": "67108864",
      "choice": [],
      "calculated": false,
      "type": "string",
      "required": "optional",
      "recipes": [],
      "mapping": "cookbook_attribute"
    },
    "hbase/memstore/preflush_trigger": {
      "display_name": "",
      "description": "hbase.hregion.preclose.flush.size (default 5 mb) -- If the memstores in a region are\nthis size or larger when we go to close, run a \"pre-flush\" to clear out memstores\nbefore we put up the region closed flag and take the region offline.  On close, a\nflush is run under the close flag to empty memory.  During this time the region is\noffline and we are not taking on any writes.  If the memstore content is large, this\nflush could take a long time to complete.  The preflush is meant to clean out the bulk\nof the memstore before putting up the close flag and taking the region offline so the\nflush that runs under the close flag has little to do.",
      "default": "5242880",
      "choice": [],
      "calculated": false,
      "type": "string",
      "required": "optional",
      "recipes": [],
      "mapping": "cookbook_attribute"
    },
    "hbase/memstore/flush_stall_trigger": {
      "display_name": "",
      "description": "hbase.hregion.memstore.block.multiplier (default 2) -- Block updates if memstore has\nhbase.hregion.block.memstore time hbase.hregion.flush.size bytes.  Useful preventing\nrunaway memstore during spikes in update traffic.  Without an upper-bound, memstore\nfills such that when it flushes the resultant flush files take a long time to compact\nor split, or worse, we OOME.",
      "default": "8",
      "choice": [],
      "calculated": false,
      "type": "string",
      "required": "optional",
      "recipes": [],
      "mapping": "cookbook_attribute"
    },
    "hbase/memstore/mslab_enabled": {
      "display_name": "",
      "description": "hbase.hregion.memstore.mslab.enabled (default false) -- Experimental: Enables the\nMemStore-Local Allocation Buffer, a feature which works to prevent heap fragmentation\nunder heavy write loads. This can reduce the frequency of stop-the-world GC pauses on\nlarge heaps.",
      "default": "",
      "choice": [],
      "calculated": false,
      "type": "string",
      "required": "optional",
      "recipes": [],
      "mapping": "cookbook_attribute"
    },
    "hbase/compaction/files_trigger": {
      "display_name": "",
      "description": "hbase.hstore.compactionThreshold (default 3) -- If more than this number of HStoreFiles\nin any one HStore (one HStoreFile is written per flush of memstore) then a compaction\nis run to rewrite all HStoreFiles files as one.  Larger numbers put off compaction but\nwhen it runs, it takes longer to complete.",
      "default": "3",
      "choice": [],
      "calculated": false,
      "type": "string",
      "required": "optional",
      "recipes": [],
      "mapping": "cookbook_attribute"
    },
    "hbase/compaction/pause_trigger": {
      "display_name": "",
      "description": "hbase.hstore.blockingStoreFiles (default 7) -- If more than this number of StoreFiles in\nany one Store (one StoreFile is written per flush of MemStore) then updates are\nblocked for this HRegion until a compaction is completed, or until\nhbase.hstore.blockingWaitTime has been exceeded.",
      "default": "7",
      "choice": [],
      "calculated": false,
      "type": "string",
      "required": "optional",
      "recipes": [],
      "mapping": "cookbook_attribute"
    },
    "hbase/compaction/pause_time": {
      "display_name": "",
      "description": "hbase.hstore.blockingWaitTime (default 90_000) -- The time an HRegion will block updates\nfor after hitting the StoreFile limit defined by hbase.hstore.blockingStoreFiles.\nAfter this time has elapsed, the HRegion will stop blocking updates even if a\ncompaction has not been completed.  Default: 90 seconds.",
      "default": "90000",
      "choice": [],
      "calculated": false,
      "type": "string",
      "required": "optional",
      "recipes": [],
      "mapping": "cookbook_attribute"
    },
    "hbase/compaction/max_combine_files": {
      "display_name": "",
      "description": "hbase.hstore.compaction.max (default 10) -- Max number of HStoreFiles to compact per\n'minor' compaction.",
      "default": "10",
      "choice": [],
      "calculated": false,
      "type": "string",
      "required": "optional",
      "recipes": [],
      "mapping": "cookbook_attribute"
    },
    "hbase/compaction/period": {
      "display_name": "",
      "description": "hbase.hregion.majorcompaction (default 86400000) -- The time (in miliseconds) between\n'major' compactions of all HStoreFiles in a region.  Default: 1 day.  Set to 0 to\ndisable automated major compactions.",
      "default": "86400000",
      "choice": [],
      "calculated": false,
      "type": "string",
      "required": "optional",
      "recipes": [],
      "mapping": "cookbook_attribute"
    },
    "users/hbase/uid": {
      "display_name": "",
      "description": "",
      "default": "304",
      "choice": [],
      "calculated": false,
      "type": "string",
      "required": "optional",
      "recipes": [],
      "mapping": "cookbook_attribute"
    },
    "tuning/ulimit/hbase": {
      "display_name": "",
      "description": "",
      "type": "hash",
      "default": {
        "nofile": {
          "both": 32768
        },
        "nproc": {
          "both": 50000
        }
      },
      "choice": [],
      "calculated": false,
      "required": "optional",
      "recipes": [],
      "mapping": "cookbook_attribute"
    }
  }
}